atl/__init__.py
atl/encryption_rsa.py
atl/example1.py
atl/example2.py
atl/log.py
tests/__init__.py
tests/test_encryption_rsa.py
tests/test_example1.py
tests/test_example2.py
tests/test_log.py
atl-1.0.dist-info/LICENSE
atl-1.0.dist-info/METADATA
atl-1.0.dist-info/WHEEL
atl-1.0.dist-info/top_level.txt
atl-1.0.dist-info/RECORD
