Metadata-Version: 2.1
Name: atl
Version: 1.0
Summary: ambedded.ch ambedded-technology-lab python3 library
Home-page: https://gitlab.com/ambedded-labs/al-pypi-ambedded-atl
Author: ambedded.ch
Author-email: info@ambedded.ch
License: GNU GENERAL PUBLIC LICENSE
Classifier: Development Status :: 4 - Beta
Classifier: Intended Audience :: Developers
Classifier: License :: OSI Approved :: GNU General Public License v2 (GPLv2)
Classifier: Programming Language :: Python :: 3
Classifier: Programming Language :: Python :: 3.6
Classifier: Programming Language :: Python :: 3.7
Classifier: Programming Language :: Python :: 3.8
Classifier: Programming Language :: Python :: 3.9
License-File: LICENSE
Requires-Dist: setuptools
Requires-Dist: cryptocompare
Requires-Dist: numpy
Requires-Dist: pycryptodome
